dynamic_prefetching_cache/__init__.py
dynamic_prefetching_cache/cache.py
dynamic_prefetching_cache/predictors.py
dynamic_prefetching_cache/providers.py
dynamic_prefetching_cache/py.typed
dynamic_prefetching_cache/types.py
dynamic_prefetching_cache-0.1.3.dist-info/licenses/LICENSE.txt
dynamic_prefetching_cache-0.1.3.dist-info/METADATA
dynamic_prefetching_cache-0.1.3.dist-info/WHEEL
dynamic_prefetching_cache-0.1.3.dist-info/top_level.txt
dynamic_prefetching_cache-0.1.3.dist-info/RECORD
