Metadata-Version: 2.4
Name: dynamic-prefetching-cache
Version: 0.1.3
Summary: A predictive caching framework that dynamically pre-loads data items with minimal latency
Author-email: Rasmus Rynell <rynell.rasmus@gmail.com>
License: MIT
Project-URL: Repository, https://github.com/rasmusrynell/dynamic-prefetching-cache
Keywords: cache,prefetch,prediction,performance,data
Classifier: Development Status :: 3 - Alpha
Classifier: Intended Audience :: Developers
Classifier: License :: OSI Approved :: MIT License
Classifier: Operating System :: OS Independent
Classifier: Programming Language :: Python :: 3
Classifier: Programming Language :: Python :: 3.8
Classifier: Programming Language :: Python :: 3.9
Classifier: Programming Language :: Python :: 3.10
Classifier: Programming Language :: Python :: 3.11
Classifier: Programming Language :: Python :: 3.12
Classifier: Topic :: Software Development :: Libraries :: Python Modules
Requires-Python: >=3.8
License-File: LICENSE.txt
Provides-Extra: dev
Requires-Dist: mypy>=1.0; extra == "dev"
Requires-Dist: pytest>=7.0; extra == "dev"
Requires-Dist: pytest-cov>=4.0; extra == "dev"
Requires-Dist: pytest-asyncio>=0.21; extra == "dev"
Provides-Extra: examples
Requires-Dist: tabulate>=0.9; extra == "examples"
Dynamic: license-file
